Workbook

Sheet 🍓 Início
B2: 🍓 Planilha de Controle de Gastos 🍓
B5: Inspirada na Moranguinho — doce, organizado e cheio de carinho 🍃
B8: 📋 Como usar esta planilha
B10: 1. | C10: Aba Receitas 💰 | E10: Lance todas as suas entradas de dinheiro (salário, freelas, etc.).
B11: 2. | C11: Aba Despesas 🧾 | E11: Lance todos os seus gastos, escolhendo a categoria e a forma de pagamento.
B12: 3. | C12: Aba Categorias e Orçamento 🎯 | E12: Defina quanto você planeja gastar em cada categoria por mês.
B13: 4. | C13: Aba Resumo Mensal 📊 | E13: Escolha o mês na célula amarela e veja o resumo automático, com gráfico.
B15: 💛 | C15: Células amarelas = você preenche. | E15: Células brancas/cinzas têm fórmulas — não precisa mexer.
B17: Legenda de cores:
C18: Preencha aqui
C19: Cálculo automático
C20: Dentro do orçamento
C21: Acima do orçamento

Sheet Resumo Mensal
A1: 📊 Resumo Mensal
A2: Escolha o mês de referência e veja o balanço automático.
A4: Mês de referência (1º dia do mês): | C4: 46266 | F4: ↖ Digite qualquer data do mês desejado, ex: 01/09/2026
B6: Total de Receitas | E6: Total de Despesas | H6: Saldo do Mês
B7: =SUMIFS(Receitas!$D$5:$D$154,Receitas!$A$5:$A$154,">="&DATE(YEAR($C$4),MONTH($C$4),1),Receitas!$A$5:$A$154,"<="&EOMONTH($C$4,0)) -> 3500 | E7: =SUMIFS(Despesas!$E$5:$E$304,Despesas!$A$5:$A$304,">="&DATE(YEAR($C$4),MONTH($C$4),1),Despesas!$A$5:$A$304,"<="&EOMONTH($C$4,0)) -> 250 | H7: =B7-E7 -> 3250
B9: 🍓 Gastos por Categoria no Mês
B10: Categoria | C10: Orçamento (R$) | D10: Gasto Real (R$) | E10: Diferença (R$) | F10: % Utilizado
B11: ='Categorias e Orçamento'!A5 -> Moradia | C11: ='Categorias e Orçamento'!B5 -> 300 | D11: =SUMIFS(Despesas!$E$5:$E$304,Despesas!$C$5:$C$304,B11,Despesas!$A$5:$A$304,">="&DATE(YEAR($C$4),MONTH($C$4),1),Despesas!$A$5:$A$304,"<="&EOMONTH($C$4,0)) -> 0 | E11: =C11-D11 -> 300 | F11: =IF(C11=0,0,D11/C11) -> 0
B12: ='Categorias e Orçamento'!A6 -> Alimentação | C12: ='Categorias e Orçamento'!B6 -> 300 | D12: =SUMIFS(Despesas!$E$5:$E$304,Despesas!$C$5:$C$304,B12,Despesas!$A$5:$A$304,">="&DATE(YEAR($C$4),MONTH($C$4),1),Despesas!$A$5:$A$304,"<="&EOMONTH($C$4,0)) -> 250 | E12: =C12-D12 -> 50 | F12: =IF(C12=0,0,D12/C12) -> 0.83333333
B13: ='Categorias e Orçamento'!A7 -> Transporte | C13: ='Categorias e Orçamento'!B7 -> 300 | D13: =SUMIFS(Despesas!$E$5:$E$304,Despesas!$C$5:$C$304,B13,Despesas!$A$5:$A$304,">="&DATE(YEAR($C$4),MONTH($C$4),1),Despesas!$A$5:$A$304,"<="&EOMONTH($C$4,0)) -> 0 | E13: =C13-D13 -> 300 | F13: =IF(C13=0,0,D13/C13) -> 0
B14: ='Categorias e Orçamento'!A8 -> Saúde | C14: ='Categorias e Orçamento'!B8 -> 300 | D14: =SUMIFS(Despesas!$E$5:$E$304,Despesas!$C$5:$C$304,B14,Despesas!$A$5:$A$304,">="&DATE(YEAR($C$4),MONTH($C$4),1),Despesas!$A$5:$A$304,"<="&EOMONTH($C$4,0)) -> 0 | E14: =C14-D14 -> 300 | F14: =IF(C14=0,0,D14/C14) -> 0
B15: ='Categorias e Orçamento'!A9 -> Educação | C15: ='Categorias e Orçamento'!B9 -> 300 | D15: =SUMIFS(Despesas!$E$5:$E$304,Despesas!$C$5:$C$304,B15,Despesas!$A$5:$A$304,">="&DATE(YEAR($C$4),MONTH($C$4),1),Despesas!$A$5:$A$304,"<="&EOMONTH($C$4,0)) -> 0 | E15: =C15-D15 -> 300 | F15: =IF(C15=0,0,D15/C15) -> 0
B16: ='Categorias e Orçamento'!A10 -> Lazer | C16: ='Categorias e Orçamento'!B10 -> 300 | D16: =SUMIFS(Despesas!$E$5:$E$304,Despesas!$C$5:$C$304,B16,Despesas!$A$5:$A$304,">="&DATE(YEAR($C$4),MONTH($C$4),1),Despesas!$A$5:$A$304,"<="&EOMONTH($C$4,0)) -> 0 | E16: =C16-D16 -> 300 | F16: =IF(C16=0,0,D16/C16) -> 0
B17: ='Categorias e Orçamento'!A11 -> Vestuário | C17: ='Categorias e Orçamento'!B11 -> 300 | D17: =SUMIFS(Despesas!$E$5:$E$304,Despesas!$C$5:$C$304,B17,Despesas!$A$5:$A$304,">="&DATE(YEAR($C$4),MONTH($C$4),1),Despesas!$A$5:$A$304,"<="&EOMONTH($C$4,0)) -> 0 | E17: =C17-D17 -> 300 | F17: =IF(C17=0,0,D17/C17) -> 0
B18: ='Categorias e Orçamento'!A12 -> Assinaturas | C18: ='Categorias e Orçamento'!B12 -> 300 | D18: =SUMIFS(Despesas!$E$5:$E$304,Despesas!$C$5:$C$304,B18,Despesas!$A$5:$A$304,">="&DATE(YEAR($C$4),MONTH($C$4),1),Despesas!$A$5:$A$304,"<="&EOMONTH($C$4,0)) -> 0 | E18: =C18-D18 -> 300 | F18: =IF(C18=0,0,D18/C18) -> 0
B19: ='Categorias e Orçamento'!A13 -> Beleza e Cuidados | C19: ='Categorias e Orçamento'!B13 -> 300 | D19: =SUMIFS(Despesas!$E$5:$E$304,Despesas!$C$5:$C$304,B19,Despesas!$A$5:$A$304,">="&DATE(YEAR($C$4),MONTH($C$4),1),Despesas!$A$5:$A$304,"<="&EOMONTH($C$4,0)) -> 0 | E19: =C19-D19 -> 300 | F19: =IF(C19=0,0,D19/C19) -> 0
B20: ='Categorias e Orçamento'!A14 -> Pets | C20: ='Categorias e Orçamento'!B14 -> 300 | D20: =SUMIFS(Despesas!$E$5:$E$304,Despesas!$C$5:$C$304,B20,Despesas!$A$5:$A$304,">="&DATE(YEAR($C$4),MONTH($C$4),1),Despesas!$A$5:$A$304,"<="&EOMONTH($C$4,0)) -> 0 | E20: =C20-D20 -> 300 | F20: =IF(C20=0,0,D20/C20) -> 0
B21: ='Categorias e Orçamento'!A15 -> Presentes | C21: ='Categorias e Orçamento'!B15 -> 300 | D21: =SUMIFS(Despesas!$E$5:$E$304,Despesas!$C$5:$C$304,B21,Despesas!$A$5:$A$304,">="&DATE(YEAR($C$4),MONTH($C$4),1),Despesas!$A$5:$A$304,"<="&EOMONTH($C$4,0)) -> 0 | E21: =C21-D21 -> 300 | F21: =IF(C21=0,0,D21/C21) -> 0
B22: ='Categorias e Orçamento'!A16 -> Outros | C22: ='Categorias e Orçamento'!B16 -> 300 | D22: =SUMIFS(Despesas!$E$5:$E$304,Despesas!$C$5:$C$304,B22,Despesas!$A$5:$A$304,">="&DATE(YEAR($C$4),MONTH($C$4),1),Despesas!$A$5:$A$304,"<="&EOMONTH($C$4,0)) -> 0 | E22: =C22-D22 -> 300 | F22: =IF(C22=0,0,D22/C22) -> 0

Sheet Receitas
A1: 💰 Receitas
A2: Lance aqui todas as entradas de dinheiro do mês.
A4: Data | B4: Descrição | C4: Categoria | D4: Valor (R$) | E4: Mês/Ano
A5: 46270 | B5: Salário mensal (exemplo) | C5: Salário | D5: 3500 | E5: =IF(A5="","",TEXT(A5,"mmm/yyyy")) -> Sep/2026
E6: =IF(A6="","",TEXT(A6,"mmm/yyyy"))
E7: =IF(A7="","",TEXT(A7,"mmm/yyyy"))
E8: =IF(A8="","",TEXT(A8,"mmm/yyyy"))
E9: =IF(A9="","",TEXT(A9,"mmm/yyyy"))
E10: =IF(A10="","",TEXT(A10,"mmm/yyyy"))
E11: =IF(A11="","",TEXT(A11,"mmm/yyyy"))
E12: =IF(A12="","",TEXT(A12,"mmm/yyyy"))
E13: =IF(A13="","",TEXT(A13,"mmm/yyyy"))
E14: =IF(A14="","",TEXT(A14,"mmm/yyyy"))
E15: =IF(A15="","",TEXT(A15,"mmm/yyyy"))
E16: =IF(A16="","",TEXT(A16,"mmm/yyyy"))
E17: =IF(A17="","",TEXT(A17,"mmm/yyyy"))
... E154: =IF(A154="","",TEXT(A154,"mmm/yyyy"))
B156: TOTAL DE RECEITAS | D156: =SUM(D5:D154) -> 3500

Sheet Despesas
A1: 🧾 Despesas
A2: Lance aqui todos os seus gastos do mês.
A4: Data | B4: Descrição | C4: Categoria | D4: Forma de Pagamento | E4: Valor (R$) | F4: Mês/Ano
A5: 46270 | B5: Supermercado (exemplo) | C5: Alimentação | D5: Débito | E5: 250 | F5: =IF(A5="","",TEXT(A5,"mmm/yyyy")) -> Sep/2026
F6: =IF(A6="","",TEXT(A6,"mmm/yyyy"))
F7: =IF(A7="","",TEXT(A7,"mmm/yyyy"))
F8: =IF(A8="","",TEXT(A8,"mmm/yyyy"))
F9: =IF(A9="","",TEXT(A9,"mmm/yyyy"))
F10: =IF(A10="","",TEXT(A10,"mmm/yyyy"))
F11: =IF(A11="","",TEXT(A11,"mmm/yyyy"))
F12: =IF(A12="","",TEXT(A12,"mmm/yyyy"))
F13: =IF(A13="","",TEXT(A13,"mmm/yyyy"))
F14: =IF(A14="","",TEXT(A14,"mmm/yyyy"))
F15: =IF(A15="","",TEXT(A15,"mmm/yyyy"))
F16: =IF(A16="","",TEXT(A16,"mmm/yyyy"))
F17: =IF(A17="","",TEXT(A17,"mmm/yyyy"))
... F304: =IF(A304="","",TEXT(A304,"mmm/yyyy"))
B306: TOTAL DE DESPESAS | E306: =SUM(E5:E304) -> 250

Sheet Categorias e Orçamento
A1: 🍓 Categorias e Orçamento Mensal
A2: Defina quanto planeja gastar em cada categoria (célula amarela).
A4: Categoria | B4: Orçamento Mensal (R$) | C4: Tipo
A5: Moradia | B5: 300 | C5: Despesa
A6: Alimentação | B6: 300 | C6: Despesa
A7: Transporte | B7: 300 | C7: Despesa
A8: Saúde | B8: 300 | C8: Despesa
A9: Educação | B9: 300 | C9: Despesa
A10: Lazer | B10: 300 | C10: Despesa
A11: Vestuário | B11: 300 | C11: Despesa
A12: Assinaturas | B12: 300 | C12: Despesa
A13: Beleza e Cuidados | B13: 300 | C13: Despesa
A14: Pets | B14: 300 | C14: Despesa
A15: Presentes | B15: 300 | C15: Despesa
A16: Outros | B16: 300 | C16: Despesa
A17: TOTAL | B17: =SUM(B5:B16) -> 3600
